<annotation>
	<folder>train</folder>
	<filename>799119045.png</filename>
	<path>E:\Data\captcha3\train\799119045.png</path>
	<source>
		<database>Unknown</database>
	</source>
	<size>
		<width>546</width>
		<height>144</height>
		<depth>3</depth>
	</size>
	<segmented>0</segmented>
	<object>
		<name>p</name>
		<pose>Unspecified</pose>
		<truncated>0</truncated>
		<difficult>0</difficult>
		<bndbox>
			<xmin>54</xmin>
			<ymin>17</ymin>
			<xmax>137</xmax>
			<ymax>140</ymax>
		</bndbox>
	</object>
	<object>
		<name>g</name>
		<pose>Unspecified</pose>
		<truncated>0</truncated>
		<difficult>0</difficult>
		<bndbox>
			<xmin>147</xmin>
			<ymin>19</ymin>
			<xmax>233</xmax>
			<ymax>143</ymax>
		</bndbox>
	</object>
	<object>
		<name>6</name>
		<pose>Unspecified</pose>
		<truncated>0</truncated>
		<difficult>0</difficult>
		<bndbox>
			<xmin>238</xmin>
			<ymin>2</ymin>
			<xmax>323</xmax>
			<ymax>120</ymax>
		</bndbox>
	</object>
	<object>
		<name>v</name>
		<pose>Unspecified</pose>
		<truncated>0</truncated>
		<difficult>0</difficult>
		<bndbox>
			<xmin>326</xmin>
			<ymin>16</ymin>
			<xmax>406</xmax>
			<ymax>113</ymax>
		</bndbox>
	</object>
	<object>
		<name>n</name>
		<pose>Unspecified</pose>
		<truncated>0</truncated>
		<difficult>0</difficult>
		<bndbox>
			<xmin>418</xmin>
			<ymin>17</ymin>
			<xmax>504</xmax>
			<ymax>122</ymax>
		</bndbox>
	</object>
</annotation>
